imcui/__init__.py
imcui/api/__init__.py
imcui/api/client.py
imcui/api/core.py
imcui/api/server.py
imcui/assets/logo.webp
imcui/cli/main.py
imcui/config/api.yaml
imcui/config/app.yaml
imcui/datasets/wxbs_benchmark/download.py
imcui/datasets/wxbs_benchmark/example.py
imcui/hloc/__init__.py
imcui/hloc/colmap_from_nvm.py
imcui/hloc/extract_features.py
imcui/hloc/localize_inloc.py
imcui/hloc/localize_sfm.py
imcui/hloc/match_dense.py
imcui/hloc/match_features.py
imcui/hloc/pairs_from_covisibility.py
imcui/hloc/pairs_from_exhaustive.py
imcui/hloc/pairs_from_poses.py
imcui/hloc/pairs_from_retrieval.py
imcui/hloc/reconstruction.py
imcui/hloc/triangulation.py
imcui/hloc/visualization.py
imcui/hloc/configs/__init__.py
imcui/hloc/configs/extractors.py
imcui/hloc/configs/matchers.py
imcui/hloc/extractors/__init__.py
imcui/hloc/extractors/alike.py
imcui/hloc/extractors/aliked.py
imcui/hloc/extractors/cosplace.py
imcui/hloc/extractors/d2net.py
imcui/hloc/extractors/darkfeat.py
imcui/hloc/extractors/dedode.py
imcui/hloc/extractors/dir.py
imcui/hloc/extractors/disk.py
imcui/hloc/extractors/dog.py
imcui/hloc/extractors/eigenplaces.py
imcui/hloc/extractors/example.py
imcui/hloc/extractors/fire.py
imcui/hloc/extractors/fire_local.py
imcui/hloc/extractors/lanet.py
imcui/hloc/extractors/liftfeat.py
imcui/hloc/extractors/netvlad.py
imcui/hloc/extractors/openibl.py
imcui/hloc/extractors/r2d2.py
imcui/hloc/extractors/rdd.py
imcui/hloc/extractors/rekd.py
imcui/hloc/extractors/ripe.py
imcui/hloc/extractors/rord.py
imcui/hloc/extractors/sfd2.py
imcui/hloc/extractors/sift.py
imcui/hloc/extractors/superpoint.py
imcui/hloc/extractors/xfeat.py
imcui/hloc/matchers/__init__.py
imcui/hloc/matchers/adalam.py
imcui/hloc/matchers/aspanformer.py
imcui/hloc/matchers/cotr.py
imcui/hloc/matchers/dad_roma.py
imcui/hloc/matchers/dkm.py
imcui/hloc/matchers/dual_softmax.py
imcui/hloc/matchers/duster.py
imcui/hloc/matchers/eloftr.py
imcui/hloc/matchers/gim.py
imcui/hloc/matchers/gluestick.py
imcui-0.0.6.dist-info/licenses/LICENSE
imcui-0.0.6.dist-info/METADATA
imcui-0.0.6.dist-info/WHEEL
imcui-0.0.6.dist-info/entry_points.txt
imcui-0.0.6.dist-info/top_level.txt
imcui-0.0.6.dist-info/RECORD
