Metadata-Version: 2.4
Name: imcui
Version: 0.0.6
Summary: Image Matching Webui: A tool for matching images using sota algorithms with a Gradio UI
Author: vincentqyw
License:                                  Apache License
Project-URL: Repository, https://github.com/Vincentqyw/image-matching-webui
Classifier: Programming Language :: Python :: 3
Classifier: License :: OSI Approved :: Apache Software License
Classifier: Operating System :: OS Independent
Classifier: Programming Language :: Python :: 3.9
Classifier: Programming Language :: Python :: 3.10
Classifier: Programming Language :: Python :: 3.11
Classifier: Programming Language :: Python :: 3.12
Requires-Python: <3.13,>=3.9
License-File: LICENSE
Requires-Dist: datasets
Requires-Dist: e2cnn
Requires-Dist: easydict
Requires-Dist: einops
Requires-Dist: fastapi
Requires-Dist: gdown
Requires-Dist: gradio
Requires-Dist: h5py
Requires-Dist: huggingface_hub
Requires-Dist: imageio
Requires-Dist: Jinja2
Requires-Dist: kornia
Requires-Dist: loguru
Requires-Dist: matplotlib<3.9
Requires-Dist: numpy~=1.24
Requires-Dist: omegaconf
Requires-Dist: onnxruntime
Requires-Dist: opencv-contrib-python
Requires-Dist: opencv-python
Requires-Dist: pandas
Requires-Dist: plotly
Requires-Dist: poselib
Requires-Dist: protobuf
Requires-Dist: psutil
Requires-Dist: pycolmap
Requires-Dist: pytlsd
Requires-Dist: pytorch-lightning
Requires-Dist: PyYAML
Requires-Dist: ray
Requires-Dist: ray[serve]
Requires-Dist: roma
Requires-Dist: scikit-image
Requires-Dist: scikit-learn
Requires-Dist: scipy
Requires-Dist: seaborn
Requires-Dist: shapely
Requires-Dist: tensorboardX
Requires-Dist: torchmetrics
Requires-Dist: torchvision
Requires-Dist: tqdm
Requires-Dist: uvicorn
Requires-Dist: yacs
Provides-Extra: dev
Requires-Dist: black; extra == "dev"
Requires-Dist: flake8; extra == "dev"
Requires-Dist: isort; extra == "dev"
Dynamic: license-file
